zope.app.exception-5.0-py3.9-nspkg.pth
zope/app/exception/__init__.py
zope/app/exception/ftesting.zcml
zope/app/exception/interfaces.py
zope/app/exception/systemerror.py
zope/app/exception/testing.py
zope/app/exception/browser/__init__.py
zope/app/exception/browser/configure.zcml
zope/app/exception/browser/notfound.pt
zope/app/exception/browser/notfound.py
zope/app/exception/browser/systemerror.pt
zope/app/exception/browser/systemerror.rst
zope/app/exception/browser/unauthorized.pt
zope/app/exception/browser/unauthorized.py
zope/app/exception/browser/user.pt
zope/app/exception/browser/user.py
zope/app/exception/browser/tests/__init__.py
zope/app/exception/browser/tests/test_error.py
zope/app/exception/browser/tests/test_unauthorized.py
zope.app.exception-5.0.dist-info/LICENSE.txt
zope.app.exception-5.0.dist-info/METADATA
zope.app.exception-5.0.dist-info/WHEEL
zope.app.exception-5.0.dist-info/namespace_packages.txt
zope.app.exception-5.0.dist-info/top_level.txt
zope.app.exception-5.0.dist-info/RECORD
