Metadata-Version: 2.1
Name: zope.app.exception
Version: 5.0
Summary: Zope 3 exception views
Home-page: http://pypi.python.org/pypi/zope.app.exception
Author: Zope Corporation and Contributors
Author-email: zope-dev@zope.dev
License: ZPL 2.1
Keywords: zope3 exception view
Classifier: Development Status :: 5 - Production/Stable
Classifier: Environment :: Web Environment
Classifier: Intended Audience :: Developers
Classifier: License :: OSI Approved :: Zope Public License
Classifier: Programming Language :: Python
Classifier: Programming Language :: Python :: 3
Classifier: Programming Language :: Python :: 3.7
Classifier: Programming Language :: Python :: 3.8
Classifier: Programming Language :: Python :: 3.9
Classifier: Programming Language :: Python :: 3.10
Classifier: Programming Language :: Python :: 3.11
Classifier: Programming Language :: Python :: Implementation :: CPython
Classifier: Programming Language :: Python :: Implementation :: PyPy
Classifier: Natural Language :: English
Classifier: Operating System :: OS Independent
Classifier: Topic :: Internet :: WWW/HTTP
Classifier: Framework :: Zope :: 3
Requires-Python: >=3.7
License-File: LICENSE.txt
Requires-Dist: setuptools
Requires-Dist: zope.interface
Requires-Dist: zope.publisher (>=3.12)
Requires-Dist: zope.authentication
Requires-Dist: zope.browser (>=1.2)
Requires-Dist: zope.browserpage (>=3.11.0)
Requires-Dist: zope.component
Requires-Dist: zope.security
Provides-Extra: test
Requires-Dist: webtest ; extra == 'test'
Requires-Dist: zope.app.appsetup ; extra == 'test'
Requires-Dist: zope.app.basicskin (>=4.0) ; extra == 'test'
Requires-Dist: zope.app.pagetemplate ; extra == 'test'
Requires-Dist: zope.app.publication ; extra == 'test'
Requires-Dist: zope.app.wsgi ; extra == 'test'
Requires-Dist: zope.browsermenu ; extra == 'test'
Requires-Dist: zope.browserresource ; extra == 'test'
Requires-Dist: zope.container ; extra == 'test'
Requires-Dist: zope.login ; extra == 'test'
Requires-Dist: zope.password ; extra == 'test'
Requires-Dist: zope.principalregistry ; extra == 'test'
Requires-Dist: zope.publisher ; extra == 'test'
Requires-Dist: zope.securitypolicy ; extra == 'test'
Requires-Dist: zope.site ; extra == 'test'
Requires-Dist: zope.testrunner ; extra == 'test'
